baseplate/__init__.py
baseplate/clients/__init__.py
baseplate/clients/cassandra.py
baseplate/clients/kombu.py
baseplate/clients/memcache/__init__.py
baseplate/clients/memcache/lib.py
baseplate/clients/redis.py
baseplate/clients/redis_cluster.py
baseplate/clients/requests.py
baseplate/clients/sqlalchemy.py
baseplate/clients/thrift.py
baseplate/frameworks/__init__.py
baseplate/frameworks/pyramid/__init__.py
baseplate/frameworks/pyramid/csrf.py
baseplate/frameworks/queue_consumer/__init__.py
baseplate/frameworks/queue_consumer/kafka.py
baseplate/frameworks/queue_consumer/kombu.py
baseplate/frameworks/thrift/__init__.py
baseplate/frameworks/thrift/command.py
baseplate/healthcheck/__init__.py
baseplate/lib/__init__.py
baseplate/lib/_requests.py
baseplate/lib/config.py
baseplate/lib/crypto.py
baseplate/lib/datetime.py
baseplate/lib/edgecontext.py
baseplate/lib/errors.py
baseplate/lib/events.py
baseplate/lib/file_watcher.py
baseplate/lib/live_data/__init__.py
baseplate/lib/live_data/writer.py
baseplate/lib/live_data/zookeeper.py
baseplate/lib/log_formatter.py
baseplate/lib/message_queue.py
baseplate/lib/metrics.py
baseplate/lib/prometheus_metrics.py
baseplate/lib/propagator_redditb3_http.py
baseplate/lib/propagator_redditb3_thrift.py
baseplate/lib/random.py
baseplate/lib/ratelimit/__init__.py
baseplate/lib/ratelimit/backends/__init__.py
baseplate/lib/ratelimit/backends/memcache.py
baseplate/lib/ratelimit/backends/redis.py
baseplate/lib/ratelimit/ratelimit.py
baseplate/lib/retry.py
baseplate/lib/secrets.py
baseplate/lib/service_discovery.py
baseplate/lib/thrift_pool.py
baseplate/lib/tracing.py
baseplate/lint/__init__.py
baseplate/lint/db_query_string_format_plugin.py
baseplate/lint/example_plugin.py
baseplate/observers/__init__.py
baseplate/observers/logging.py
baseplate/observers/metrics.py
baseplate/observers/metrics_tagged.py
baseplate/observers/sentry.py
baseplate/observers/timeout.py
baseplate/observers/tracing.py
baseplate/py.typed
baseplate/server/__init__.py
baseplate-2.7.1.dist-info/LICENSE
baseplate-2.7.1.dist-info/METADATA
baseplate-2.7.1.dist-info/WHEEL
baseplate-2.7.1.dist-info/entry_points.txt
baseplate-2.7.1.dist-info/RECORD
