Metadata-Version: 2.1
Name: baseplate
Version: 2.7.1
Summary: reddit's python service framework
Home-page: https://github.com/reddit/baseplate.py
License: BSD
Author: reddit
Requires-Python: >=3.8.1,<4.0
Classifier: Development Status :: 5 - Production/Stable
Classifier: License :: OSI Approved :: BSD License
Classifier: License :: Other/Proprietary License
Classifier: Operating System :: POSIX :: Linux
Classifier: Programming Language :: Python :: 3
Classifier: Programming Language :: Python :: 3.9
Classifier: Programming Language :: Python :: 3.10
Classifier: Programming Language :: Python :: 3.11
Classifier: Programming Language :: Python :: 3.12
Classifier: Topic :: Software Development :: Libraries
Classifier: Topic :: Software Development :: Libraries :: Application Frameworks
Provides-Extra: amqp
Provides-Extra: cassandra
Provides-Extra: cqlmapper
Provides-Extra: kafka
Provides-Extra: memcache
Provides-Extra: prometheus
Provides-Extra: psycopg2
Provides-Extra: pyramid
Provides-Extra: redis
Provides-Extra: redis-py-cluster
Provides-Extra: refcycle
Provides-Extra: requests
Provides-Extra: s3fetcher
Provides-Extra: sentry
Provides-Extra: sql
Provides-Extra: zookeeper
Requires-Dist: advocate (>=1.0.0,<2.0) ; extra == "requests"
Requires-Dist: boto3 (>=1.28.27)
Requires-Dist: cassandra-driver (>=3.29.0,<4.0) ; extra == "cassandra"
Requires-Dist: confluent-kafka (>=2.3.0) ; extra == "kafka"
Requires-Dist: formenergy-observability (>=0.3.2,<0.4.0)
Requires-Dist: gevent (>=23.9.1)
Requires-Dist: kazoo (>=2.5.0,<3.0) ; extra == "zookeeper"
Requires-Dist: kombu (>=5.3.3) ; extra == "amqp"
Requires-Dist: objgraph (>=3.6.0) ; extra == "refcycle"
Requires-Dist: opentelemetry-api (>=1.26.0,<2.0.0)
Requires-Dist: opentelemetry-exporter-otlp (>=1.26.0,<2.0.0)
Requires-Dist: opentelemetry-instrumentation-logging (>=0.47b0,<0.48)
Requires-Dist: opentelemetry-instrumentation-pyramid (>=0.47b0,<0.48)
Requires-Dist: opentelemetry-instrumentation-requests (>=0.47b0,<0.48)
Requires-Dist: opentelemetry-instrumentation-threading (>=0.47b0,<0.48)
Requires-Dist: opentelemetry-sdk (>=1.26.0,<2.0.0)
Requires-Dist: posix-ipc (>=1.0.0,<2.0)
Requires-Dist: prometheus-client (>=0.12.0)
Requires-Dist: psycogreen (>=1.0.0,<2.0.0) ; extra == "psycopg2"
Requires-Dist: psycopg2 (>=2.0.0,<3.0.0) ; extra == "psycopg2"
Requires-Dist: pymemcache (>=1.3.0,<1.4.4) ; extra == "memcache"
Requires-Dist: pyramid (>=1.10.8,<2.0) ; extra == "pyramid"
Requires-Dist: pyrate-limiter (>=3.6.1,<4.0.0)
Requires-Dist: python-json-logger (>=2.0.5,<3.0)
Requires-Dist: reddit-cqlmapper (>=0.3.0,<1.0) ; extra == "cqlmapper"
Requires-Dist: redis (>=2.10.0,<4.0.0) ; extra == "redis"
Requires-Dist: redis-py-cluster (>=2.1.2,<3.0.0) ; extra == "redis-py-cluster"
Requires-Dist: requests (>=2.21.0,<3.0)
Requires-Dist: sentry-sdk (>=1.35.0,<2.0) ; extra == "sentry"
Requires-Dist: sqlalchemy (>=1.4.49,<2) ; extra == "sql"
Requires-Dist: thrift-unofficial (>=0.19.0,<1.0)
Requires-Dist: typing-extensions (>=4.11.0,<5.0.0)
Project-URL: Documentation, https://baseplate.readthedocs.io/en/stable/
Project-URL: Repository, https://github.com/reddit/baseplate.py
